odoo/addons/currency_rate_update_boi/README.rst
odoo/addons/currency_rate_update_boi/__init__.py
odoo/addons/currency_rate_update_boi/__manifest__.py
odoo/addons/currency_rate_update_boi/i18n/currency_rate_update_boi.pot
odoo/addons/currency_rate_update_boi/i18n/it.po
odoo/addons/currency_rate_update_boi/models/__init__.py
odoo/addons/currency_rate_update_boi/models/res_currency_rate_provider_BOI.py
odoo/addons/currency_rate_update_boi/readme/CONFIGURE.rst
odoo/addons/currency_rate_update_boi/readme/CONTRIBUTORS.rst
odoo/addons/currency_rate_update_boi/readme/DESCRIPTION.rst
odoo/addons/currency_rate_update_boi/static/description/icon.png
odoo/addons/currency_rate_update_boi/static/description/index.html
odoo12_addon_currency_rate_update_boi-12.0.1.0.0.99.dev10.dist-info/METADATA
odoo12_addon_currency_rate_update_boi-12.0.1.0.0.99.dev10.dist-info/WHEEL
odoo12_addon_currency_rate_update_boi-12.0.1.0.0.99.dev10.dist-info/top_level.txt
odoo12_addon_currency_rate_update_boi-12.0.1.0.0.99.dev10.dist-info/RECORD
